receptorctl/__init__.py
receptorctl/__main__.py
receptorctl/cli.py
receptorctl/socket_interface.py
receptorctl-1.6.3.dist-info/METADATA
receptorctl-1.6.3.dist-info/WHEEL
receptorctl-1.6.3.dist-info/entry_points.txt
receptorctl-1.6.3.dist-info/top_level.txt
receptorctl-1.6.3.dist-info/RECORD
