Metadata-Version: 2.4
Name: receptorctl
Version: 1.6.3
Summary: Receptorctl is a front-end CLI and importable Python library that interacts with Receptor over its control socket interface.
Author-email: Red Hat <info@ansible.com>
License: Apache-2.0
Project-URL: Homepage, https://ansible.readthedocs.io/projects/receptor/
Project-URL: Documentation, https://ansible.readthedocs.io/projects/receptor/en/latest/
Project-URL: Repository, https://github.com/ansible/receptor
Project-URL: Issues, https://github.com/ansible/receptor/issues
Requires-Dist: python-dateutil>=2.8.1
Requires-Dist: click<8.2.0,>=8.1.3
Requires-Dist: PyYAML>=5.4.1
Provides-Extra: test
Requires-Dist: coverage; extra == "test"
Requires-Dist: pip-tools>=7; extra == "test"
Requires-Dist: pytest; extra == "test"
Requires-Dist: pytest-cov; extra == "test"
Requires-Dist: ruff; extra == "test"
